testincessantly/__init__.py
testincessantly/__main__.py
testincessantly/debounce.py
testincessantly/exclusion.py
testincessantly/notification.py
testincessantly/restartableprocess.py
testincessantly-0.1.3.dist-info/DESCRIPTION.rst
testincessantly-0.1.3.dist-info/METADATA
testincessantly-0.1.3.dist-info/RECORD
testincessantly-0.1.3.dist-info/WHEEL
testincessantly-0.1.3.dist-info/entry_points.txt
testincessantly-0.1.3.dist-info/metadata.json
testincessantly-0.1.3.dist-info/top_level.txt
