Metadata-Version: 2.0
Name: testincessantly
Version: 0.1.3
Summary: A tool to run your tests way more often than necessary.
Home-page: https://github.com/speezepearson/testincessantly
Author: speezepearson
Author-email: speeze.pearson@gmail.com
License: UNKNOWN
Keywords: test tool command-line
Platform: UNKNOWN
Classifier: Development Status :: 3 - Alpha
Classifier: Intended Audience :: Developers
Classifier: Topic :: Software Development :: Testing
Classifier: Programming Language :: Python :: 3
Classifier: Programming Language :: Python :: 3.2
Classifier: Programming Language :: Python :: 3.3
Classifier: Programming Language :: Python :: 3.4
Classifier: Programming Language :: Python :: 3.5
Requires-Dist: inotify
Provides-Extra: dev
Provides-Extra: test
Requires-Dist: pytest; extra == 'test'
